[{"match_id":968318,"stats":{"MIN":45,"GL":0,"ASS":0,"CS":0,"SV":0,"PE":0,"PS":0,"PM":0,"GC":3,"YC":0,"RC":0,"OG":0,"OGA":0,"SH":0,"WF":0,"PSS":4,"APS":4,"CRS":0,"KP":0,"BC":0,"CL":1,"BLK":2,"INT":1,"TCK":0,"BR":1,"ELG":0}},{"match_id":968329,"stats":{"MIN":90,"GL":0,"ASS":0,"CS":1,"SV":0,"PE":0,"PS":0,"PM":0,"GC":0,"YC":0,"RC":0,"OG":0,"OGA":0,"SH":0,"WF":0,"PSS":21,"APS":16,"CRS":0,"KP":1,"BC":1,"CL":7,"BLK":0,"INT":1,"TCK":1,"BR":4,"ELG":0}},{"round_id":"all","stats":{"MIN":135,"GL":0,"ASS":0,"CS":1,"SV":0,"PE":0,"PS":0,"PM":0,"GC":3,"YC":0,"RC":0,"OG":0,"OGA":0,"SH":0,"WF":0,"PSS":25,"APS":20,"CRS":0,"KP":1,"BC":1,"CL":8,"BLK":2,"INT":2,"TCK":1,"BR":5,"ELG":0}}]