[{"match_id":965467,"stats":{"MIN":25,"GL":1,"ASS":0,"CS":1,"SV":0,"PE":0,"PS":0,"PM":0,"GC":0,"YC":0,"RC":0,"OG":0,"OGA":0,"SH":2,"WF":0,"PSS":7,"APS":2,"CRS":0,"KP":0,"BC":0,"CL":0,"BLK":0,"INT":0,"TCK":1,"BR":0,"ELG":0}},{"match_id":968280,"stats":{"MIN":26,"GL":0,"ASS":0,"CS":1,"SV":0,"PE":0,"PS":0,"PM":0,"GC":0,"YC":1,"RC":0,"OG":0,"OGA":0,"SH":1,"WF":1,"PSS":6,"APS":2,"CRS":0,"KP":0,"BC":0,"CL":0,"BLK":0,"INT":0,"TCK":0,"BR":1,"ELG":0}},{"match_id":968300,"stats":{"MIN":13,"GL":0,"ASS":0,"CS":0,"SV":0,"PE":0,"PS":0,"PM":0,"GC":1,"YC":0,"RC":0,"OG":0,"OGA":0,"SH":0,"WF":2,"PSS":4,"APS":1,"CRS":0,"KP":0,"BC":0,"CL":0,"BLK":0,"INT":0,"TCK":0,"BR":1,"ELG":0}},{"match_id":968486,"stats":{"MIN":14,"GL":0,"ASS":0,"CS":0,"SV":0,"PE":0,"PS":0,"PM":0,"GC":1,"YC":1,"RC":0,"OG":1,"OGA":0,"SH":0,"WF":1,"PSS":5,"APS":4,"CRS":0,"KP":0,"BC":0,"CL":0,"BLK":0,"INT":0,"TCK":0,"BR":0,"ELG":0}},{"match_id":968497,"stats":{"MIN":16,"GL":0,"ASS":0,"CS":1,"SV":0,"PE":0,"PS":0,"PM":0,"GC":0,"YC":0,"RC":0,"OG":0,"OGA":0,"SH":0,"WF":1,"PSS":6,"APS":3,"CRS":0,"KP":0,"BC":0,"CL":0,"BLK":0,"INT":0,"TCK":1,"BR":0,"ELG":0}},{"match_id":968508,"stats":{"MIN":17,"GL":0,"ASS":0,"CS":1,"SV":0,"PE":0,"PS":0,"PM":0,"GC":0,"YC":0,"RC":0,"OG":0,"OGA":0,"SH":2,"WF":1,"PSS":5,"APS":4,"CRS":0,"KP":0,"BC":0,"CL":0,"BLK":0,"INT":0,"TCK":0,"BR":1,"ELG":0}},{"match_id":968523,"stats":{"MIN":62,"GL":0,"ASS":0,"CS":0,"SV":0,"PE":0,"PS":0,"PM":0,"GC":2,"YC":1,"RC":0,"OG":0,"OGA":0,"SH":3,"WF":5,"PSS":13,"APS":9,"CRS":0,"KP":1,"BC":0,"CL":0,"BLK":0,"INT":0,"TCK":1,"BR":4,"ELG":0}},{"match_id":968536,"stats":{"MIN":9,"GL":0,"ASS":0,"CS":0,"SV":0,"PE":0,"PS":0,"PM":0,"GC":6,"YC":0,"RC":1,"OG":0,"OGA":0,"SH":0,"WF":0,"PSS":0,"APS":0,"CRS":0,"KP":0,"BC":0,"CL":0,"BLK":0,"INT":0,"TCK":0,"BR":0,"ELG":0}},{"match_id":968544,"stats":{"MIN":27,"GL":1,"ASS":0,"CS":0,"SV":0,"PE":0,"PS":0,"PM":0,"GC":1,"YC":0,"RC":0,"OG":0,"OGA":0,"SH":2,"WF":2,"PSS":8,"APS":4,"CRS":0,"KP":1,"BC":0,"CL":0,"BLK":0,"INT":1,"TCK":0,"BR":1,"ELG":0}},{"match_id":968561,"stats":{"MIN":45,"GL":0,"ASS":0,"CS":1,"SV":0,"PE":0,"PS":0,"PM":0,"GC":0,"YC":0,"RC":0,"OG":0,"OGA":0,"SH":2,"WF":0,"PSS":4,"APS":3,"CRS":0,"KP":0,"BC":0,"CL":0,"BLK":0,"INT":0,"TCK":0,"BR":0,"ELG":0}},{"match_id":968575,"stats":{"MIN":23,"GL":0,"ASS":0,"CS":1,"SV":0,"PE":0,"PS":0,"PM":0,"GC":0,"YC":0,"RC":0,"OG":0,"OGA":0,"SH":0,"WF":1,"PSS":2,"APS":1,"CRS":0,"KP":0,"BC":0,"CL":0,"BLK":0,"INT":0,"TCK":0,"BR":0,"ELG":0}},{"round_id":"all","stats":{"MIN":277,"GL":2,"ASS":0,"CS":6,"SV":0,"PE":0,"PS":0,"PM":0,"GC":11,"YC":3,"RC":1,"OG":1,"OGA":0,"SH":12,"WF":14,"PSS":60,"APS":33,"CRS":0,"KP":2,"BC":0,"CL":0,"BLK":0,"INT":1,"TCK":3,"BR":8,"ELG":0}}]