{"history_past":[{"id":1571,"season_name":"2014","element_code":132113,"start_cost":45,"end_cost":55,"total_points":106,"minutes":2086,"goals_scored":2,"assists":3,"clean_sheets":5,"penalties_earned":1,"penalties_conceded":0,"penalties_saved":0,"penalties_missed":0,"goals_conceded":38,"own_goals":1,"yellow_cards":2,"red_cards":2,"saves":0,"crosses":1,"key_passes":11,"big_chances_created":1,"clearances":0,"blocks":0,"interceptions":0,"tackles":0,"recoveries":110,"errors_leading_to_goal":1,"own_goal_earned":0,"pass_completion":0,"shots":0,"was_fouled":0,"season":3},{"id":2202,"season_name":"2015","element_code":132113,"start_cost":60,"end_cost":59,"total_points":36,"minutes":790,"goals_scored":0,"assists":1,"clean_sheets":2,"penalties_earned":0,"penalties_conceded":0,"penalties_saved":0,"penalties_missed":0,"goals_conceded":18,"own_goals":0,"yellow_cards":4,"red_cards":0,"saves":0,"crosses":2,"key_passes":5,"big_chances_created":2,"clearances":0,"blocks":0,"interceptions":0,"tackles":0,"recoveries":34,"errors_leading_to_goal":0,"own_goal_earned":0,"pass_completion":0,"shots":0,"was_fouled":0,"season":4},{"id":2835,"season_name":"2016","element_code":132113,"start_cost":65,"end_cost":66,"total_points":40,"minutes":854,"goals_scored":0,"assists":0,"clean_sheets":1,"penalties_earned":0,"penalties_conceded":0,"penalties_saved":0,"penalties_missed":0,"goals_conceded":10,"own_goals":0,"yellow_cards":0,"red_cards":0,"saves":0,"crosses":2,"key_passes":4,"big_chances_created":3,"clearances":45,"blocks":7,"interceptions":22,"tackles":9,"recoveries":35,"errors_leading_to_goal":0,"own_goal_earned":0,"pass_completion":0,"shots":3,"was_fouled":6,"season":5}],"fixtures_summary":[],"explain":[{"explain":{"minutes":{"points":0,"name":"Minutes played","value":0}},"fixture":{"id":364,"kickoff_time_formatted":"Oct 22 4:00PM EDT","started":true,"event_day":1,"deadline_time":"2017-10-22T20:00:00Z","deadline_time_formatted":"Oct 22 4:00PM EDT","stats":[{"goals_scored":{"a":[{"value":1,"element":460},{"value":1,"element":462}],"h":[{"value":1,"element":504},{"value":1,"element":542}]}},{"assists":{"a":[{"value":1,"element":449}],"h":[{"value":1,"element":503},{"value":1,"element":516}]}},{"penalties_earned":{"a":[],"h":[]}},{"penalties_conceded":{"a":[],"h":[]}},{"penalties_saved":{"a":[],"h":[]}},{"penalties_missed":{"a":[],"h":[]}},{"own_goals":{"a":[],"h":[]}},{"yellow_cards":{"a":[{"value":1,"element":465}],"h":[{"value":1,"element":510}]}},{"red_cards":{"a":[],"h":[]}},{"saves":{"a":[{"value":2,"element":444}],"h":[{"value":4,"element":625}]}},{"crosses":{"a":[{"value":3,"element":571},{"value":1,"element":460}],"h":[{"value":2,"element":516},{"value":1,"element":80},{"value":1,"element":504},{"value":1,"element":509},{"value":1,"element":511}]}},{"key_passes":{"a":[{"value":4,"element":571},{"value":2,"element":459},{"value":1,"element":449},{"value":1,"element":451},{"value":1,"element":453}],"h":[{"value":3,"element":504},{"value":3,"element":507},{"value":2,"element":516},{"value":1,"element":80},{"value":1,"element":503},{"value":1,"element":509}]}},{"big_chances_created":{"a":[{"value":2,"element":459},{"value":1,"element":449},{"value":1,"element":571}],"h":[{"value":1,"element":503},{"value":1,"element":516}]}},{"clearances":{"a":[{"value":8,"element":465},{"value":3,"element":447},{"value":2,"element":449},{"value":2,"element":457},{"value":1,"element":451},{"value":1,"element":460}],"h":[{"value":7,"element":499},{"value":4,"element":510},{"value":3,"element":518},{"value":2,"element":548},{"value":1,"element":80}]}},{"blocks":{"a":[{"value":1,"element":447},{"value":1,"element":451},{"value":1,"element":457},{"value":1,"element":465}],"h":[{"value":1,"element":518}]}},{"interceptions":{"a":[{"value":4,"element":451},{"value":3,"element":453},{"value":2,"element":447},{"value":2,"element":449},{"value":1,"element":457}],"h":[{"value":3,"element":504},{"value":3,"element":518},{"value":2,"element":507},{"value":2,"element":509},{"value":2,"element":510},{"value":1,"element":80},{"value":1,"element":499},{"value":1,"element":511}]}},{"tackles":{"a":[{"value":4,"element":457},{"value":3,"element":453},{"value":2,"element":447},{"value":2,"element":449},{"value":1,"element":451},{"value":1,"element":456},{"value":1,"element":459},{"value":1,"element":465}],"h":[{"value":3,"element":509},{"value":3,"element":548},{"value":2,"element":499},{"value":2,"element":518},{"value":2,"element":542},{"value":1,"element":504},{"value":1,"element":511},{"value":1,"element":516}]}},{"recoveries":{"a":[{"value":11,"element":453},{"value":9,"element":449},{"value":9,"element":465},{"value":8,"element":444},{"value":6,"element":457},{"value":4,"element":451},{"value":3,"element":447},{"value":3,"element":459},{"value":3,"element":571},{"value":1,"element":456},{"value":1,"element":460},{"value":1,"element":462}],"h":[{"value":13,"element":625},{"value":11,"element":548},{"value":8,"element":507},{"value":6,"element":499},{"value":4,"element":503},{"value":4,"element":510},{"value":3,"element":504},{"value":3,"element":511},{"value":3,"element":516},{"value":2,"element":518},{"value":2,"element":542},{"value":1,"element":80},{"value":1,"element":509}]}},{"errors_leading_to_goal":{"a":[],"h":[]}},{"own_goal_earned":{"a":[],"h":[]}},{"pass_completion":{"a":[{"value":1,"element":449},{"value":1,"element":453}],"h":[{"value":2,"element":518},{"value":1,"element":510}]}},{"shots":{"a":[{"value":5,"element":460},{"value":5,"element":462},{"value":1,"element":459}],"h":[{"value":3,"element":504},{"value":2,"element":507},{"value":2,"element":510},{"value":2,"element":511},{"value":2,"element":516},{"value":1,"element":80},{"value":1,"element":518},{"value":1,"element":542},{"value":1,"element":548}]}},{"was_fouled":{"a":[{"value":2,"element":459},{"value":1,"element":447},{"value":1,"element":449},{"value":1,"element":451},{"value":1,"element":460},{"value":1,"element":462}],"h":[{"value":3,"element":510},{"value":1,"element":507},{"value":1,"element":509},{"value":1,"element":516},{"value":1,"element":548}]}}],"code":902470,"kickoff_time":"2017-10-22T20:00:00Z","team_h_score":2,"team_a_score":2,"finished":true,"minutes":90,"provisional_start_time":false,"event":33,"team_a":19,"team_h":21}}],"history_summary":[{"id":19668,"kickoff_time":"2017-09-30T23:00:00Z","kickoff_time_formatted":"Sep 30 7:00PM EDT","team_h_score":4,"team_a_score":2,"was_home":true,"round":30,"total_points":0,"value":53,"transfers_balance":0,"selected":165,"transfers_in":3,"transfers_out":3,"loaned_in":0,"loaned_out":0,"minutes":0,"goals_scored":0,"assists":0,"clean_sheets":0,"penalties_earned":0,"penalties_conceded":0,"penalties_saved":0,"penalties_missed":0,"goals_conceded":0,"own_goals":0,"yellow_cards":0,"red_cards":0,"saves":0,"crosses":0,"key_passes":0,"big_chances_created":0,"clearances":0,"blocks":0,"interceptions":0,"tackles":0,"recoveries":0,"errors_leading_to_goal":0,"own_goal_earned":0,"pass_completion":0,"shots":0,"was_fouled":0,"attempted_passes":0,"completed_passes":0,"element":448,"fixture":343,"opponent_team":11},{"id":20799,"kickoff_time":"2017-10-15T21:00:00Z","kickoff_time_formatted":"Oct 15 5:00PM EDT","team_h_score":1,"team_a_score":0,"was_home":true,"round":32,"total_points":0,"value":53,"transfers_balance":4,"selected":167,"transfers_in":8,"transfers_out":4,"loaned_in":0,"loaned_out":0,"minutes":0,"goals_scored":0,"assists":0,"clean_sheets":0,"penalties_earned":0,"penalties_conceded":0,"penalties_saved":0,"penalties_missed":0,"goals_conceded":0,"own_goals":0,"yellow_cards":0,"red_cards":0,"saves":0,"crosses":0,"key_passes":0,"big_chances_created":0,"clearances":0,"blocks":0,"interceptions":0,"tackles":0,"recoveries":0,"errors_leading_to_goal":0,"own_goal_earned":0,"pass_completion":0,"shots":0,"was_fouled":0,"attempted_passes":0,"completed_passes":0,"element":448,"fixture":362,"opponent_team":7},{"id":21469,"kickoff_time":"2017-10-22T20:00:00Z","kickoff_time_formatted":"Oct 22 4:00PM EDT","team_h_score":2,"team_a_score":2,"was_home":false,"round":33,"total_points":0,"value":53,"transfers_balance":-3,"selected":165,"transfers_in":0,"transfers_out":3,"loaned_in":0,"loaned_out":0,"minutes":0,"goals_scored":0,"assists":0,"clean_sheets":0,"penalties_earned":0,"penalties_conceded":0,"penalties_saved":0,"penalties_missed":0,"goals_conceded":0,"own_goals":0,"yellow_cards":0,"red_cards":0,"saves":0,"crosses":0,"key_passes":0,"big_chances_created":0,"clearances":0,"blocks":0,"interceptions":0,"tackles":0,"recoveries":0,"errors_leading_to_goal":0,"own_goal_earned":0,"pass_completion":0,"shots":0,"was_fouled":0,"attempted_passes":0,"completed_passes":0,"element":448,"fixture":364,"opponent_team":21}],"fixtures":[],"history":[{"id":448,"kickoff_time":"2017-03-04T21:30:00Z","kickoff_time_formatted":"Mar 04 4:30PM EST","team_h_score":0,"team_a_score":0,"was_home":false,"round":1,"total_points":7,"value":50,"transfers_balance":0,"selected":90,"transfers_in":0,"transfers_out":0,"loaned_in":0,"loaned_out":0,"minutes":90,"goals_scored":0,"assists":0,"clean_sheets":1,"penalties_earned":0,"penalties_conceded":0,"penalties_saved":0,"penalties_missed":0,"goals_conceded":0,"own_goals":0,"yellow_cards":1,"red_cards":0,"saves":0,"crosses":0,"key_passes":1,"big_chances_created":0,"clearances":3,"blocks":0,"interceptions":1,"tackles":0,"recoveries":8,"errors_leading_to_goal":0,"own_goal_earned":0,"pass_completion":0,"shots":0,"was_fouled":1,"attempted_passes":56,"completed_passes":41,"element":448,"fixture":5,"opponent_team":15},{"id":997,"kickoff_time":"2017-03-11T21:30:00Z","kickoff_time_formatted":"Mar 11 4:30PM EST","team_h_score":2,"team_a_score":2,"was_home":false,"round":2,"total_points":2,"value":50,"transfers_balance":14,"selected":135,"transfers_in":39,"transfers_out":25,"loaned_in":0,"loaned_out":0,"minutes":90,"goals_scored":0,"assists":0,"clean_sheets":0,"penalties_earned":0,"penalties_conceded":0,"penalties_saved":0,"penalties_missed":0,"goals_conceded":2,"own_goals":0,"yellow_cards":0,"red_cards":0,"saves":0,"crosses":0,"key_passes":0,"big_chances_created":0,"clearances":3,"blocks":1,"interceptions":3,"tackles":2,"recoveries":7,"errors_leading_to_goal":0,"own_goal_earned":0,"pass_completion":0,"shots":0,"was_fouled":0,"attempted_passes":44,"completed_passes":30,"element":448,"fixture":15,"opponent_team":13},{"id":1594,"kickoff_time":"2017-03-18T20:00:00Z","kickoff_time_formatted":"Mar 18 4:00PM EDT","team_h_score":0,"team_a_score":2,"was_home":false,"round":3,"total_points":7,"value":49,"transfers_balance":-26,"selected":115,"transfers_in":14,"transfers_out":40,"loaned_in":0,"loaned_out":0,"minutes":74,"goals_scored":0,"assists":0,"clean_sheets":1,"penalties_earned":0,"penalties_conceded":0,"penalties_saved":0,"penalties_missed":0,"goals_conceded":0,"own_goals":0,"yellow_cards":0,"red_cards":0,"saves":0,"crosses":0,"key_passes":0,"big_chances_created":0,"clearances":3,"blocks":0,"interceptions":1,"tackles":1,"recoveries":3,"errors_leading_to_goal":0,"own_goal_earned":0,"pass_completion":0,"shots":2,"was_fouled":2,"attempted_passes":57,"completed_passes":46,"element":448,"fixture":24,"opponent_team":20},{"id":2312,"kickoff_time":"2017-03-31T23:30:00Z","kickoff_time_formatted":"Mar 31 7:30PM EDT","team_h_score":0,"team_a_score":0,"was_home":true,"round":5,"total_points":7,"value":50,"transfers_balance":236,"selected":346,"transfers_in":302,"transfers_out":66,"loaned_in":0,"loaned_out":0,"minutes":90,"goals_scored":0,"assists":0,"clean_sheets":1,"penalties_earned":0,"penalties_conceded":0,"penalties_saved":0,"penalties_missed":0,"goals_conceded":0,"own_goals":0,"yellow_cards":0,"red_cards":0,"saves":0,"crosses":1,"key_passes":1,"big_chances_created":0,"clearances":3,"blocks":1,"interceptions":3,"tackles":1,"recoveries":5,"errors_leading_to_goal":0,"own_goal_earned":0,"pass_completion":0,"shots":0,"was_fouled":0,"attempted_passes":59,"completed_passes":46,"element":448,"fixture":41,"opponent_team":18},{"id":2918,"kickoff_time":"2017-04-08T23:30:00Z","kickoff_time_formatted":"Apr 08 7:30PM EDT","team_h_score":2,"team_a_score":2,"was_home":true,"round":6,"total_points":0,"value":51,"transfers_balance":-117,"selected":234,"transfers_in":97,"transfers_out":214,"loaned_in":0,"loaned_out":0,"minutes":40,"goals_scored":0,"assists":0,"clean_sheets":0,"penalties_earned":0,"penalties_conceded":0,"penalties_saved":0,"penalties_missed":0,"goals_conceded":0,"own_goals":0,"yellow_cards":1,"red_cards":0,"saves":0,"crosses":0,"key_passes":0,"big_chances_created":0,"clearances":0,"blocks":0,"interceptions":0,"tackles":1,"recoveries":3,"errors_leading_to_goal":0,"own_goal_earned":0,"pass_completion":0,"shots":1,"was_fouled":1,"attempted_passes":28,"completed_passes":25,"element":448,"fixture":53,"opponent_team":21},{"id":3534,"kickoff_time":"2017-04-16T00:00:00Z","kickoff_time_formatted":"Apr 15 8:00PM EDT","team_h_score":2,"team_a_score":1,"was_home":false,"round":7,"total_points":4,"value":51,"transfers_balance":-70,"selected":165,"transfers_in":4,"transfers_out":74,"loaned_in":0,"loaned_out":0,"minutes":90,"goals_scored":0,"assists":0,"clean_sheets":0,"penalties_earned":0,"penalties_conceded":0,"penalties_saved":0,"penalties_missed":0,"goals_conceded":2,"own_goals":0,"yellow_cards":0,"red_cards":0,"saves":0,"crosses":0,"key_passes":0,"big_chances_created":0,"clearances":7,"blocks":4,"interceptions":2,"tackles":2,"recoveries":3,"errors_leading_to_goal":0,"own_goal_earned":0,"pass_completion":0,"shots":1,"was_fouled":0,"attempted_passes":56,"completed_passes":46,"element":448,"fixture":63,"opponent_team":3},{"id":4192,"kickoff_time":"2017-04-21T23:30:00Z","kickoff_time_formatted":"Apr 21 7:30PM EDT","team_h_score":3,"team_a_score":1,"was_home":true,"round":8,"total_points":4,"value":51,"transfers_balance":3,"selected":170,"transfers_in":22,"transfers_out":19,"loaned_in":0,"loaned_out":0,"minutes":90,"goals_scored":0,"assists":0,"clean_sheets":0,"penalties_earned":0,"penalties_conceded":0,"penalties_saved":0,"penalties_missed":0,"goals_conceded":1,"own_goals":0,"yellow_cards":0,"red_cards":0,"saves":0,"crosses":0,"key_passes":0,"big_chances_created":0,"clearances":8,"blocks":1,"interceptions":2,"tackles":1,"recoveries":3,"errors_leading_to_goal":0,"own_goal_earned":0,"pass_completion":0,"shots":1,"was_fouled":1,"attempted_passes":43,"completed_passes":32,"element":448,"fixture":71,"opponent_team":1},{"id":4811,"kickoff_time":"2017-04-28T23:30:00Z","kickoff_time_formatted":"Apr 28 7:30PM EDT","team_h_score":2,"team_a_score":0,"was_home":true,"round":9,"total_points":9,"value":51,"transfers_balance":26,"selected":199,"transfers_in":58,"transfers_out":32,"loaned_in":0,"loaned_out":0,"minutes":90,"goals_scored":0,"assists":0,"clean_sheets":1,"penalties_earned":0,"penalties_conceded":0,"penalties_saved":0,"penalties_missed":0,"goals_conceded":0,"own_goals":0,"yellow_cards":0,"red_cards":0,"saves":0,"crosses":0,"key_passes":0,"big_chances_created":0,"clearances":6,"blocks":3,"interceptions":0,"tackles":1,"recoveries":5,"errors_leading_to_goal":0,"own_goal_earned":0,"pass_completion":0,"shots":0,"was_fouled":0,"attempted_passes":54,"completed_passes":42,"element":448,"fixture":82,"opponent_team":6},{"id":5509,"kickoff_time":"2017-05-03T23:30:00Z","kickoff_time_formatted":"May 03 7:30PM EDT","team_h_score":2,"team_a_score":1,"was_home":true,"round":10,"total_points":4,"value":52,"transfers_balance":152,"selected":354,"transfers_in":209,"transfers_out":57,"loaned_in":0,"loaned_out":0,"minutes":90,"goals_scored":0,"assists":0,"clean_sheets":0,"penalties_earned":0,"penalties_conceded":0,"penalties_saved":0,"penalties_missed":0,"goals_conceded":1,"own_goals":0,"yellow_cards":0,"red_cards":0,"saves":0,"crosses":0,"key_passes":0,"big_chances_created":0,"clearances":9,"blocks":0,"interceptions":3,"tackles":3,"recoveries":3,"errors_leading_to_goal":0,"own_goal_earned":0,"pass_completion":0,"shots":2,"was_fouled":1,"attempted_passes":31,"completed_passes":25,"element":448,"fixture":93,"opponent_team":12},{"id":5510,"kickoff_time":"2017-05-06T19:00:00Z","kickoff_time_formatted":"May 06 3:00PM EDT","team_h_score":0,"team_a_score":1,"was_home":false,"round":10,"total_points":9,"value":52,"transfers_balance":152,"selected":354,"transfers_in":209,"transfers_out":57,"loaned_in":0,"loaned_out":0,"minutes":90,"goals_scored":0,"assists":0,"clean_sheets":1,"penalties_earned":0,"penalties_conceded":0,"penalties_saved":0,"penalties_missed":0,"goals_conceded":0,"own_goals":0,"yellow_cards":0,"red_cards":0,"saves":0,"crosses":0,"key_passes":0,"big_chances_created":0,"clearances":10,"blocks":0,"interceptions":0,"tackles":2,"recoveries":4,"errors_leading_to_goal":0,"own_goal_earned":0,"pass_completion":0,"shots":0,"was_fouled":0,"attempted_passes":29,"completed_passes":25,"element":448,"fixture":97,"opponent_team":17},{"id":6188,"kickoff_time":"2017-05-10T23:30:00Z","kickoff_time_formatted":"May 10 7:30PM EDT","team_h_score":1,"team_a_score":2,"was_home":false,"round":11,"total_points":7,"value":53,"transfers_balance":1733,"selected":2107,"transfers_in":2071,"transfers_out":338,"loaned_in":0,"loaned_out":0,"minutes":90,"goals_scored":0,"assists":0,"clean_sheets":0,"penalties_earned":0,"penalties_conceded":0,"penalties_saved":0,"penalties_missed":0,"goals_conceded":1,"own_goals":0,"yellow_cards":0,"red_cards":0,"saves":0,"crosses":0,"key_passes":0,"big_chances_created":0,"clearances":7,"blocks":5,"interceptions":0,"tackles":4,"recoveries":4,"errors_leading_to_goal":0,"own_goal_earned":0,"pass_completion":1,"shots":0,"was_fouled":1,"attempted_passes":51,"completed_passes":45,"element":448,"fixture":106,"opponent_team":3},{"id":6189,"kickoff_time":"2017-05-13T19:00:00Z","kickoff_time_formatted":"May 13 3:00PM EDT","team_h_score":3,"team_a_score":2,"was_home":true,"round":11,"total_points":1,"value":53,"transfers_balance":1733,"selected":2107,"transfers_in":2071,"transfers_out":338,"loaned_in":0,"loaned_out":0,"minutes":64,"goals_scored":0,"assists":0,"clean_sheets":0,"penalties_earned":0,"penalties_conceded":0,"penalties_saved":0,"penalties_missed":0,"goals_conceded":2,"own_goals":0,"yellow_cards":0,"red_cards":0,"saves":0,"crosses":0,"key_passes":0,"big_chances_created":0,"clearances":3,"blocks":0,"interceptions":0,"tackles":1,"recoveries":3,"errors_leading_to_goal":0,"own_goal_earned":0,"pass_completion":0,"shots":1,"was_fouled":0,"attempted_passes":44,"completed_passes":34,"element":448,"fixture":110,"opponent_team":22},{"id":7071,"kickoff_time":"2017-05-19T23:30:00Z","kickoff_time_formatted":"May 19 7:30PM EDT","team_h_score":1,"team_a_score":1,"was_home":false,"round":12,"total_points":0,"value":53,"transfers_balance":-1754,"selected":355,"transfers_in":23,"transfers_out":1777,"loaned_in":0,"loaned_out":0,"minutes":0,"goals_scored":0,"assists":0,"clean_sheets":0,"penalties_earned":0,"penalties_conceded":0,"penalties_saved":0,"penalties_missed":0,"goals_conceded":0,"own_goals":0,"yellow_cards":0,"red_cards":0,"saves":0,"crosses":0,"key_passes":0,"big_chances_created":0,"clearances":0,"blocks":0,"interceptions":0,"tackles":0,"recoveries":0,"errors_leading_to_goal":0,"own_goal_earned":0,"pass_completion":0,"shots":0,"was_fouled":0,"attempted_passes":0,"completed_passes":0,"element":448,"fixture":123,"opponent_team":11},{"id":7738,"kickoff_time":"2017-05-26T23:00:00Z","kickoff_time_formatted":"May 26 7:00PM EDT","team_h_score":5,"team_a_score":0,"was_home":true,"round":13,"total_points":0,"value":53,"transfers_balance":-129,"selected":226,"transfers_in":0,"transfers_out":129,"loaned_in":0,"loaned_out":0,"minutes":0,"goals_scored":0,"assists":0,"clean_sheets":0,"penalties_earned":0,"penalties_conceded":0,"penalties_saved":0,"penalties_missed":0,"goals_conceded":0,"own_goals":0,"yellow_cards":0,"red_cards":0,"saves":0,"crosses":0,"key_passes":0,"big_chances_created":0,"clearances":0,"blocks":0,"interceptions":0,"tackles":0,"recoveries":0,"errors_leading_to_goal":0,"own_goal_earned":0,"pass_completion":0,"shots":0,"was_fouled":0,"attempted_passes":0,"completed_passes":0,"element":448,"fixture":134,"opponent_team":3},{"id":8553,"kickoff_time":"2017-06-03T23:30:00Z","kickoff_time_formatted":"Jun 03 7:30PM EDT","team_h_score":3,"team_a_score":0,"was_home":false,"round":14,"total_points":0,"value":53,"transfers_balance":-28,"selected":198,"transfers_in":0,"transfers_out":28,"loaned_in":0,"loaned_out":0,"minutes":0,"goals_scored":0,"assists":0,"clean_sheets":0,"penalties_earned":0,"penalties_conceded":0,"penalties_saved":0,"penalties_missed":0,"goals_conceded":0,"own_goals":0,"yellow_cards":0,"red_cards":0,"saves":0,"crosses":0,"key_passes":0,"big_chances_created":0,"clearances":0,"blocks":0,"interceptions":0,"tackles":0,"recoveries":0,"errors_leading_to_goal":0,"own_goal_earned":0,"pass_completion":0,"shots":0,"was_fouled":0,"attempted_passes":0,"completed_passes":0,"element":448,"fixture":151,"opponent_team":9},{"id":9380,"kickoff_time":"2017-06-18T00:00:00Z","kickoff_time_formatted":"Jun 17 8:00PM EDT","team_h_score":2,"team_a_score":0,"was_home":true,"round":16,"total_points":0,"value":53,"transfers_balance":-8,"selected":176,"transfers_in":2,"transfers_out":10,"loaned_in":0,"loaned_out":0,"minutes":0,"goals_scored":0,"assists":0,"clean_sheets":0,"penalties_earned":0,"penalties_conceded":0,"penalties_saved":0,"penalties_missed":0,"goals_conceded":0,"own_goals":0,"yellow_cards":0,"red_cards":0,"saves":0,"crosses":0,"key_passes":0,"big_chances_created":0,"clearances":0,"blocks":0,"interceptions":0,"tackles":0,"recoveries":0,"errors_leading_to_goal":0,"own_goal_earned":0,"pass_completion":0,"shots":0,"was_fouled":0,"attempted_passes":0,"completed_passes":0,"element":448,"fixture":166,"opponent_team":4},{"id":10155,"kickoff_time":"2017-06-24T00:00:00Z","kickoff_time_formatted":"Jun 23 8:00PM EDT","team_h_score":2,"team_a_score":0,"was_home":true,"round":17,"total_points":0,"value":53,"transfers_balance":-3,"selected":173,"transfers_in":1,"transfers_out":4,"loaned_in":0,"loaned_out":0,"minutes":0,"goals_scored":0,"assists":0,"clean_sheets":0,"penalties_earned":0,"penalties_conceded":0,"penalties_saved":0,"penalties_missed":0,"goals_conceded":0,"own_goals":0,"yellow_cards":0,"red_cards":0,"saves":0,"crosses":0,"key_passes":0,"big_chances_created":0,"clearances":0,"blocks":0,"interceptions":0,"tackles":0,"recoveries":0,"errors_leading_to_goal":0,"own_goal_earned":0,"pass_completion":0,"shots":0,"was_fouled":0,"attempted_passes":0,"completed_passes":0,"element":448,"fixture":179,"opponent_team":9},{"id":10802,"kickoff_time":"2017-07-01T23:00:00Z","kickoff_time_formatted":"Jul 01 7:00PM EDT","team_h_score":3,"team_a_score":1,"was_home":false,"round":18,"total_points":0,"value":53,"transfers_balance":-3,"selected":170,"transfers_in":0,"transfers_out":3,"loaned_in":0,"loaned_out":0,"minutes":0,"goals_scored":0,"assists":0,"clean_sheets":0,"penalties_earned":0,"penalties_conceded":0,"penalties_saved":0,"penalties_missed":0,"goals_conceded":0,"own_goals":0,"yellow_cards":0,"red_cards":0,"saves":0,"crosses":0,"key_passes":0,"big_chances_created":0,"clearances":0,"blocks":0,"interceptions":0,"tackles":0,"recoveries":0,"errors_leading_to_goal":0,"own_goal_earned":0,"pass_completion":0,"shots":0,"was_fouled":0,"attempted_passes":0,"completed_passes":0,"element":448,"fixture":192,"opponent_team":5},{"id":11421,"kickoff_time":"2017-07-05T23:30:00Z","kickoff_time_formatted":"Jul 05 7:30PM EDT","team_h_score":1,"team_a_score":3,"was_home":false,"round":19,"total_points":0,"value":53,"transfers_balance":-4,"selected":166,"transfers_in":0,"transfers_out":4,"loaned_in":0,"loaned_out":0,"minutes":0,"goals_scored":0,"assists":0,"clean_sheets":0,"penalties_earned":0,"penalties_conceded":0,"penalties_saved":0,"penalties_missed":0,"goals_conceded":0,"own_goals":0,"yellow_cards":0,"red_cards":0,"saves":0,"crosses":0,"key_passes":0,"big_chances_created":0,"clearances":0,"blocks":0,"interceptions":0,"tackles":0,"recoveries":0,"errors_leading_to_goal":0,"own_goal_earned":0,"pass_completion":0,"shots":0,"was_fouled":0,"attempted_passes":0,"completed_passes":0,"element":448,"fixture":206,"opponent_team":12},{"id":12319,"kickoff_time":"2017-07-19T23:30:00Z","kickoff_time_formatted":"Jul 19 7:30PM EDT","team_h_score":2,"team_a_score":2,"was_home":false,"round":20,"total_points":0,"value":53,"transfers_balance":-1,"selected":165,"transfers_in":0,"transfers_out":1,"loaned_in":0,"loaned_out":0,"minutes":0,"goals_scored":0,"assists":0,"clean_sheets":0,"penalties_earned":0,"penalties_conceded":0,"penalties_saved":0,"penalties_missed":0,"goals_conceded":0,"own_goals":0,"yellow_cards":0,"red_cards":0,"saves":0,"crosses":0,"key_passes":0,"big_chances_created":0,"clearances":0,"blocks":0,"interceptions":0,"tackles":0,"recoveries":0,"errors_leading_to_goal":0,"own_goal_earned":0,"pass_completion":0,"shots":0,"was_fouled":0,"attempted_passes":0,"completed_passes":0,"element":448,"fixture":213,"opponent_team":10},{"id":12320,"kickoff_time":"2017-07-22T23:00:00Z","kickoff_time_formatted":"Jul 22 7:00PM EDT","team_h_score":1,"team_a_score":1,"was_home":true,"round":20,"total_points":4,"value":53,"transfers_balance":-1,"selected":165,"transfers_in":0,"transfers_out":1,"loaned_in":0,"loaned_out":0,"minutes":90,"goals_scored":0,"assists":0,"clean_sheets":0,"penalties_earned":0,"penalties_conceded":0,"penalties_saved":0,"penalties_missed":0,"goals_conceded":1,"own_goals":0,"yellow_cards":0,"red_cards":0,"saves":0,"crosses":0,"key_passes":0,"big_chances_created":0,"clearances":4,"blocks":1,"interceptions":2,"tackles":0,"recoveries":3,"errors_leading_to_goal":0,"own_goal_earned":0,"pass_completion":1,"shots":1,"was_fouled":0,"attempted_passes":57,"completed_passes":49,"element":448,"fixture":222,"opponent_team":2},{"id":13140,"kickoff_time":"2017-07-30T18:00:00Z","kickoff_time_formatted":"Jul 30 2:00PM EDT","team_h_score":4,"team_a_score":0,"was_home":true,"round":21,"total_points":1,"value":53,"transfers_balance":4,"selected":169,"transfers_in":11,"transfers_out":7,"loaned_in":0,"loaned_out":0,"minutes":27,"goals_scored":0,"assists":0,"clean_sheets":0,"penalties_earned":0,"penalties_conceded":0,"penalties_saved":0,"penalties_missed":0,"goals_conceded":0,"own_goals":0,"yellow_cards":0,"red_cards":0,"saves":0,"crosses":0,"key_passes":0,"big_chances_created":0,"clearances":0,"blocks":0,"interceptions":0,"tackles":0,"recoveries":1,"errors_leading_to_goal":0,"own_goal_earned":0,"pass_completion":0,"shots":0,"was_fouled":0,"attempted_passes":13,"completed_passes":9,"element":448,"fixture":240,"opponent_team":10},{"id":13790,"kickoff_time":"2017-08-05T23:00:00Z","kickoff_time_formatted":"Aug 05 7:00PM EDT","team_h_score":1,"team_a_score":1,"was_home":false,"round":22,"total_points":0,"value":53,"transfers_balance":3,"selected":172,"transfers_in":15,"transfers_out":12,"loaned_in":0,"loaned_out":0,"minutes":0,"goals_scored":0,"assists":0,"clean_sheets":0,"penalties_earned":0,"penalties_conceded":0,"penalties_saved":0,"penalties_missed":0,"goals_conceded":0,"own_goals":0,"yellow_cards":0,"red_cards":0,"saves":0,"crosses":0,"key_passes":0,"big_chances_created":0,"clearances":0,"blocks":0,"interceptions":0,"tackles":0,"recoveries":0,"errors_leading_to_goal":0,"own_goal_earned":0,"pass_completion":0,"shots":0,"was_fouled":0,"attempted_passes":0,"completed_passes":0,"element":448,"fixture":242,"opponent_team":4},{"id":14431,"kickoff_time":"2017-08-12T22:00:00Z","kickoff_time_formatted":"Aug 12 6:00PM EDT","team_h_score":4,"team_a_score":1,"was_home":true,"round":23,"total_points":1,"value":53,"transfers_balance":0,"selected":174,"transfers_in":5,"transfers_out":5,"loaned_in":0,"loaned_out":0,"minutes":18,"goals_scored":0,"assists":0,"clean_sheets":0,"penalties_earned":0,"penalties_conceded":0,"penalties_saved":0,"penalties_missed":0,"goals_conceded":0,"own_goals":0,"yellow_cards":0,"red_cards":0,"saves":0,"crosses":0,"key_passes":0,"big_chances_created":0,"clearances":0,"blocks":0,"interceptions":2,"tackles":1,"recoveries":1,"errors_leading_to_goal":0,"own_goal_earned":0,"pass_completion":0,"shots":0,"was_fouled":0,"attempted_passes":6,"completed_passes":6,"element":448,"fixture":255,"opponent_team":14},{"id":15063,"kickoff_time":"2017-08-20T00:00:00Z","kickoff_time_formatted":"Aug 19 8:00PM EDT","team_h_score":1,"team_a_score":3,"was_home":false,"round":24,"total_points":0,"value":53,"transfers_balance":-7,"selected":167,"transfers_in":0,"transfers_out":7,"loaned_in":0,"loaned_out":0,"minutes":0,"goals_scored":0,"assists":0,"clean_sheets":0,"penalties_earned":0,"penalties_conceded":0,"penalties_saved":0,"penalties_missed":0,"goals_conceded":0,"own_goals":0,"yellow_cards":0,"red_cards":0,"saves":0,"crosses":0,"key_passes":0,"big_chances_created":0,"clearances":0,"blocks":0,"interceptions":0,"tackles":0,"recoveries":0,"errors_leading_to_goal":0,"own_goal_earned":0,"pass_completion":0,"shots":0,"was_fouled":0,"attempted_passes":0,"completed_passes":0,"element":448,"fixture":265,"opponent_team":1},{"id":15966,"kickoff_time":"2017-08-24T00:00:00Z","kickoff_time_formatted":"Aug 23 8:00PM EDT","team_h_score":3,"team_a_score":0,"was_home":true,"round":25,"total_points":0,"value":53,"transfers_balance":-1,"selected":166,"transfers_in":0,"transfers_out":1,"loaned_in":0,"loaned_out":0,"minutes":0,"goals_scored":0,"assists":0,"clean_sheets":0,"penalties_earned":0,"penalties_conceded":0,"penalties_saved":0,"penalties_missed":0,"goals_conceded":0,"own_goals":0,"yellow_cards":0,"red_cards":0,"saves":0,"crosses":0,"key_passes":0,"big_chances_created":0,"clearances":0,"blocks":0,"interceptions":0,"tackles":0,"recoveries":0,"errors_leading_to_goal":0,"own_goal_earned":0,"pass_completion":0,"shots":0,"was_fouled":0,"attempted_passes":0,"completed_passes":0,"element":448,"fixture":275,"opponent_team":13},{"id":15967,"kickoff_time":"2017-08-27T20:30:00Z","kickoff_time_formatted":"Aug 27 4:30PM EDT","team_h_score":1,"team_a_score":3,"was_home":false,"round":25,"total_points":0,"value":53,"transfers_balance":-1,"selected":166,"transfers_in":0,"transfers_out":1,"loaned_in":0,"loaned_out":0,"minutes":0,"goals_scored":0,"assists":0,"clean_sheets":0,"penalties_earned":0,"penalties_conceded":0,"penalties_saved":0,"penalties_missed":0,"goals_conceded":0,"own_goals":0,"yellow_cards":0,"red_cards":0,"saves":0,"crosses":0,"key_passes":0,"big_chances_created":0,"clearances":0,"blocks":0,"interceptions":0,"tackles":0,"recoveries":0,"errors_leading_to_goal":0,"own_goal_earned":0,"pass_completion":0,"shots":0,"was_fouled":0,"attempted_passes":0,"completed_passes":0,"element":448,"fixture":288,"opponent_team":7},{"id":17071,"kickoff_time":"2017-09-09T21:00:00Z","kickoff_time_formatted":"Sep 09 5:00PM EDT","team_h_score":4,"team_a_score":0,"was_home":true,"round":27,"total_points":0,"value":53,"transfers_balance":0,"selected":165,"transfers_in":0,"transfers_out":0,"loaned_in":0,"loaned_out":0,"minutes":0,"goals_scored":0,"assists":0,"clean_sheets":0,"penalties_earned":0,"penalties_conceded":0,"penalties_saved":0,"penalties_missed":0,"goals_conceded":0,"own_goals":0,"yellow_cards":0,"red_cards":0,"saves":0,"crosses":0,"key_passes":0,"big_chances_created":0,"clearances":0,"blocks":0,"interceptions":0,"tackles":0,"recoveries":0,"errors_leading_to_goal":0,"own_goal_earned":0,"pass_completion":0,"shots":0,"was_fouled":0,"attempted_passes":0,"completed_passes":0,"element":448,"fixture":299,"opponent_team":16},{"id":17778,"kickoff_time":"2017-09-17T02:30:00Z","kickoff_time_formatted":"Sep 16 10:30PM EDT","team_h_score":0,"team_a_score":4,"was_home":false,"round":28,"total_points":0,"value":53,"transfers_balance":0,"selected":165,"transfers_in":0,"transfers_out":0,"loaned_in":0,"loaned_out":0,"minutes":0,"goals_scored":0,"assists":0,"clean_sheets":0,"penalties_earned":0,"penalties_conceded":0,"penalties_saved":0,"penalties_missed":0,"goals_conceded":0,"own_goals":0,"yellow_cards":0,"red_cards":0,"saves":0,"crosses":0,"key_passes":0,"big_chances_created":0,"clearances":0,"blocks":0,"interceptions":0,"tackles":0,"recoveries":0,"errors_leading_to_goal":0,"own_goal_earned":0,"pass_completion":0,"shots":0,"was_fouled":0,"attempted_passes":0,"completed_passes":0,"element":448,"fixture":310,"opponent_team":8},{"id":18592,"kickoff_time":"2017-09-20T23:30:00Z","kickoff_time_formatted":"Sep 20 7:30PM EDT","team_h_score":3,"team_a_score":5,"was_home":true,"round":29,"total_points":0,"value":53,"transfers_balance":0,"selected":165,"transfers_in":0,"transfers_out":0,"loaned_in":0,"loaned_out":0,"minutes":0,"goals_scored":0,"assists":0,"clean_sheets":0,"penalties_earned":0,"penalties_conceded":0,"penalties_saved":0,"penalties_missed":0,"goals_conceded":0,"own_goals":0,"yellow_cards":0,"red_cards":0,"saves":0,"crosses":0,"key_passes":0,"big_chances_created":0,"clearances":0,"blocks":0,"interceptions":0,"tackles":0,"recoveries":0,"errors_leading_to_goal":0,"own_goal_earned":0,"pass_completion":0,"shots":0,"was_fouled":0,"attempted_passes":0,"completed_passes":0,"element":448,"fixture":320,"opponent_team":7},{"id":18593,"kickoff_time":"2017-09-23T21:00:00Z","kickoff_time_formatted":"Sep 23 5:00PM EDT","team_h_score":2,"team_a_score":1,"was_home":false,"round":29,"total_points":0,"value":53,"transfers_balance":0,"selected":165,"transfers_in":0,"transfers_out":0,"loaned_in":0,"loaned_out":0,"minutes":0,"goals_scored":0,"assists":0,"clean_sheets":0,"penalties_earned":0,"penalties_conceded":0,"penalties_saved":0,"penalties_missed":0,"goals_conceded":0,"own_goals":0,"yellow_cards":0,"red_cards":0,"saves":0,"crosses":0,"key_passes":0,"big_chances_created":0,"clearances":0,"blocks":0,"interceptions":0,"tackles":0,"recoveries":0,"errors_leading_to_goal":0,"own_goal_earned":0,"pass_completion":0,"shots":0,"was_fouled":0,"attempted_passes":0,"completed_passes":0,"element":448,"fixture":322,"opponent_team":9},{"id":19668,"kickoff_time":"2017-09-30T23:00:00Z","kickoff_time_formatted":"Sep 30 7:00PM EDT","team_h_score":4,"team_a_score":2,"was_home":true,"round":30,"total_points":0,"value":53,"transfers_balance":0,"selected":165,"transfers_in":3,"transfers_out":3,"loaned_in":0,"loaned_out":0,"minutes":0,"goals_scored":0,"assists":0,"clean_sheets":0,"penalties_earned":0,"penalties_conceded":0,"penalties_saved":0,"penalties_missed":0,"goals_conceded":0,"own_goals":0,"yellow_cards":0,"red_cards":0,"saves":0,"crosses":0,"key_passes":0,"big_chances_created":0,"clearances":0,"blocks":0,"interceptions":0,"tackles":0,"recoveries":0,"errors_leading_to_goal":0,"own_goal_earned":0,"pass_completion":0,"shots":0,"was_fouled":0,"attempted_passes":0,"completed_passes":0,"element":448,"fixture":343,"opponent_team":11},{"id":20799,"kickoff_time":"2017-10-15T21:00:00Z","kickoff_time_formatted":"Oct 15 5:00PM EDT","team_h_score":1,"team_a_score":0,"was_home":true,"round":32,"total_points":0,"value":53,"transfers_balance":4,"selected":167,"transfers_in":8,"transfers_out":4,"loaned_in":0,"loaned_out":0,"minutes":0,"goals_scored":0,"assists":0,"clean_sheets":0,"penalties_earned":0,"penalties_conceded":0,"penalties_saved":0,"penalties_missed":0,"goals_conceded":0,"own_goals":0,"yellow_cards":0,"red_cards":0,"saves":0,"crosses":0,"key_passes":0,"big_chances_created":0,"clearances":0,"blocks":0,"interceptions":0,"tackles":0,"recoveries":0,"errors_leading_to_goal":0,"own_goal_earned":0,"pass_completion":0,"shots":0,"was_fouled":0,"attempted_passes":0,"completed_passes":0,"element":448,"fixture":362,"opponent_team":7},{"id":21469,"kickoff_time":"2017-10-22T20:00:00Z","kickoff_time_formatted":"Oct 22 4:00PM EDT","team_h_score":2,"team_a_score":2,"was_home":false,"round":33,"total_points":0,"value":53,"transfers_balance":-3,"selected":165,"transfers_in":0,"transfers_out":3,"loaned_in":0,"loaned_out":0,"minutes":0,"goals_scored":0,"assists":0,"clean_sheets":0,"penalties_earned":0,"penalties_conceded":0,"penalties_saved":0,"penalties_missed":0,"goals_conceded":0,"own_goals":0,"yellow_cards":0,"red_cards":0,"saves":0,"crosses":0,"key_passes":0,"big_chances_created":0,"clearances":0,"blocks":0,"interceptions":0,"tackles":0,"recoveries":0,"errors_leading_to_goal":0,"own_goal_earned":0,"pass_completion":0,"shots":0,"was_fouled":0,"attempted_passes":0,"completed_passes":0,"element":448,"fixture":364,"opponent_team":21}]}